[{"confidence": "0.9959", "file_id": "47", "bbox": "356 178 383 205"}, {"confidence": "0.9956", "file_id": "164", "bbox": "333 74 347 88"}, {"confidence": "0.9955", "file_id": "33", "bbox": "199 110 227 139"}, {"confidence": "0.9954", "file_id": "89", "bbox": "86 278 128 321"}, {"confidence": "0.9948", "file_id": "144", "bbox": "386 373 414 401"}, {"confidence": "0.9940", "file_id": "21", "bbox": "48 126 132 211"}, {"confidence": "0.9938", "file_id": "182", "bbox": "136 366 164 394"}, {"confidence": "0.9935", "file_id": "156", "bbox": "229 143 257 170"}, {"confidence": "0.9932", "file_id": "15", "bbox": "28 267 42 281"}, {"confidence": "0.9930", "file_id": "138", "bbox": "364 75 378 89"}, {"confidence": "0.9928", "file_id": "72", "bbox": "260 14 300 55"}, {"confidence": "0.9928", "file_id": "189", "bbox": "33 92 116 176"}, {"confidence": "0.9926", "file_id": "86", "bbox": "318 94 360 136"}, {"confidence": "0.9925", "file_id": "95", "bbox": "224 367 246 390"}, {"confidence": "0.9925", "file_id": "126", "bbox": "41 13 125 98"}, {"confidence": "0.9922", "file_id": "70", "bbox": "208 170 292 254"}, {"confidence": "0.9919", "file_id": "157", "bbox": "384 31 412 59"}, {"confidence": "0.9917", "file_id": "160", "bbox": "120 202 177 259"}, {"confidence": "0.9916", "file_id": "171", "bbox": "81 30 164 114"}, {"confidence": "0.9914", "file_id": "154", "bbox": "39 332 92 385"}, {"confidence": "0.9912", "file_id": "146", "bbox": "116 3 226 112"}, {"confidence": "0.9911", "file_id": "105", "bbox": "40 213 96 270"}, {"confidence": "0.9909", "file_id": "32", "bbox": "82 240 195 353"}, {"confidence": "0.9906", "file_id": "45", "bbox": "244 63 356 174"}, {"confidence": "0.9904", "file_id": "14", "bbox": "79 119 122 161"}, {"confidence": "0.9904", "file_id": "132", "bbox": "97 246 138 287"}, {"confidence": "0.9903", "file_id": "47", "bbox": "272 98 355 182"}, {"confidence": "0.9900", "file_id": "190", "bbox": "205 255 316 368"}, {"confidence": "0.9899", "file_id": "14", "bbox": "144 59 200 114"}, {"confidence": "0.9898", "file_id": "9", "bbox": "325 330 381 386"}, {"confidence": "0.9898", "file_id": "158", "bbox": "112 205 154 247"}, {"confidence": "0.9897", "file_id": "71", "bbox": "184 240 239 295"}, {"confidence": "0.9897", "file_id": "91", "bbox": "15 150 71 206"}, {"confidence": "0.9896", "file_id": "157", "bbox": "178 186 233 241"}, {"confidence": "0.9895", "file_id": "60", "bbox": "162 207 190 235"}, {"confidence": "0.9894", "file_id": "101", "bbox": "257 111 338 193"}, {"confidence": "0.9893", "file_id": "80", "bbox": "350 326 407 384"}, {"confidence": "0.9893", "file_id": "142", "bbox": "103 203 160 260"}, {"confidence": "0.9893", "file_id": "170", "bbox": "254 39 296 81"}, {"confidence": "0.9892", "file_id": "59", "bbox": "8 279 36 308"}, {"confidence": "0.9890", "file_id": "56", "bbox": "91 155 133 197"}, {"confidence": "0.9889", "file_id": "177", "bbox": "368 204 396 232"}, {"confidence": "0.9889", "file_id": "184", "bbox": "0 237 55 293"}, {"confidence": "0.9887", "file_id": "0", "bbox": "247 359 261 373"}, {"confidence": "0.9887", "file_id": "60", "bbox": "198 107 280 189"}, {"confidence": "0.9886", "file_id": "71", "bbox": "367 176 409 218"}, {"confidence": "0.9885", "file_id": "46", "bbox": "0 201 43 244"}, {"confidence": "0.9884", "file_id": "136", "bbox": "243 253 284 294"}, {"confidence": "0.9883", "file_id": "2", "bbox": "142 246 170 275"}, {"confidence": "0.9882", "file_id": "170", "bbox": "90 322 112 345"}, {"confidence": "0.9881", "file_id": "35", "bbox": "11 238 37 264"}, {"confidence": "0.9880", "file_id": "9", "bbox": "14 131 28 145"}, {"confidence": "0.9880", "file_id": "181", "bbox": "115 206 140 231"}, {"confidence": "0.9879", "file_id": "45", "bbox": "75 246 131 302"}, {"confidence": "0.9879", "file_id": "112", "bbox": "92 0 134 42"}, {"confidence": "0.9878", "file_id": "56", "bbox": "388 242 402 256"}, {"confidence": "0.9877", "file_id": "163", "bbox": "82 90 136 144"}, {"confidence": "0.9874", "file_id": "143", "bbox": "304 320 331 348"}, {"confidence": "0.9873", "file_id": "192", "bbox": "217 119 238 141"}, {"confidence": "0.9873", "file_id": "194", "bbox": "196 268 237 309"}, {"confidence": "0.9870", "file_id": "25", "bbox": "50 83 71 104"}, {"confidence": "0.9870", "file_id": "42", "bbox": "141 37 195 91"}, {"confidence": "0.9870", "file_id": "73", "bbox": "7 47 48 89"}, {"confidence": "0.9868", "file_id": "3", "bbox": "136 324 164 353"}, {"confidence": "0.9866", "file_id": "101", "bbox": "129 181 239 291"}, {"confidence": "0.9866", "file_id": "138", "bbox": "259 8 300 50"}, {"confidence": "0.9865", "file_id": "85", "bbox": "246 77 295 127"}, {"confidence": "0.9861", "file_id": "141", "bbox": "11 51 123 164"}, {"confidence": "0.9860", "file_id": "145", "bbox": "256 176 311 232"}, {"confidence": "0.9856", "file_id": "181", "bbox": "50 289 92 330"}, {"confidence": "0.9855", "file_id": "86", "bbox": "383 133 406 155"}, {"confidence": "0.9854", "file_id": "157", "bbox": "347 248 373 275"}, {"confidence": "0.9852", "file_id": "65", "bbox": "185 369 207 391"}, {"confidence": "0.9848", "file_id": "96", "bbox": "298 203 320 225"}, {"confidence": "0.9846", "file_id": "105", "bbox": "273 280 358 365"}, {"confidence": "0.9842", "file_id": "122", "bbox": "325 96 347 119"}, {"confidence": "0.9841", "file_id": "39", "bbox": "306 135 320 149"}, {"confidence": "0.9840", "file_id": "16", "bbox": "173 249 215 292"}, {"confidence": "0.9839", "file_id": "169", "bbox": "387 114 408 136"}, {"confidence": "0.9838", "file_id": "168", "bbox": "188 314 242 368"}, {"confidence": "0.9836", "file_id": "152", "bbox": "147 207 161 221"}, {"confidence": "0.9835", "file_id": "138", "bbox": "250 181 291 223"}, {"confidence": "0.9827", "file_id": "47", "bbox": "9 80 52 123"}, {"confidence": "0.9824", "file_id": "5", "bbox": "128 376 150 398"}, {"confidence": "0.9820", "file_id": "2", "bbox": "339 131 365 157"}, {"confidence": "0.9820", "file_id": "11", "bbox": "263 330 291 358"}, {"confidence": "0.9820", "file_id": "30", "bbox": "266 331 308 374"}, {"confidence": "0.9815", "file_id": "57", "bbox": "251 14 354 117"}, {"confidence": "0.9813", "file_id": "180", "bbox": "282 367 323 410"}, {"confidence": "0.9802", "file_id": "168", "bbox": "284 383 298 398"}, {"confidence": "0.9800", "file_id": "95", "bbox": "218 98 246 126"}, {"confidence": "0.9793", "file_id": "170", "bbox": "187 237 209 259"}, {"confidence": "0.9789", "file_id": "67", "bbox": "27 177 109 260"}, {"confidence": "0.9784", "file_id": "175", "bbox": "363 249 384 271"}, {"confidence": "0.9781", "file_id": "50", "bbox": "258 114 313 170"}, {"confidence": "0.9779", "file_id": "194", "bbox": "153 301 179 327"}, {"confidence": "0.9777", "file_id": "159", "bbox": "76 321 116 362"}, {"confidence": "0.9775", "file_id": "66", "bbox": "180 97 236 153"}, {"confidence": "0.9767", "file_id": "112", "bbox": "2 50 58 106"}, {"confidence": "0.9747", "file_id": "13", "bbox": "131 169 242 281"}, {"confidence": "0.9740", "file_id": "176", "bbox": "86 1 108 22"}, {"confidence": "0.9737", "file_id": "195", "bbox": "77 159 91 174"}, {"confidence": "0.9726", "file_id": "81", "bbox": "248 300 275 328"}, {"confidence": "0.9716", "file_id": "38", "bbox": "182 325 236 379"}, {"confidence": "0.9702", "file_id": "55", "bbox": "312 63 326 77"}, {"confidence": "0.9680", "file_id": "144", "bbox": "347 104 370 127"}, {"confidence": "0.9654", "file_id": "166", "bbox": "275 219 298 241"}, {"confidence": "0.9602", "file_id": "123", "bbox": "292 293 313 315"}, {"confidence": "0.9545", "file_id": "187", "bbox": "28 142 70 184"}, {"confidence": "0.9501", "file_id": "56", "bbox": "123 73 152 103"}, {"confidence": "0.9459", "file_id": "43", "bbox": "299 340 322 363"}, {"confidence": "0.9386", "file_id": "84", "bbox": "214 358 268 411"}, {"confidence": "0.9127", "file_id": "44", "bbox": "310 275 324 290"}, {"confidence": "0.6438", "file_id": "116", "bbox": "105 342 161 399"}]